sao_download/__init__.py
sao_download/download.py
niu_download-1.1.0.dist-info/METADATA
niu_download-1.1.0.dist-info/WHEEL
niu_download-1.1.0.dist-info/entry_points.txt
niu_download-1.1.0.dist-info/top_level.txt
niu_download-1.1.0.dist-info/RECORD
