Metadata-Version: 2.1
Name: niu-download
Version: 1.1.0
Summary: A tool that can download Hugging Face model(s)
Home-page: https://github.com/342215448/HF-models-Download-batch.git
Author: Peinan Feng & Junhao Ruan & Peizhuo Liu (NEUNLPLAB)
Author-email: fpnan@foxmail.com
Project-URL: Bug Tracker, https://github.com/pypa/sampleproject/issues
Classifier: Programming Language :: Python :: 3
Classifier: License :: OSI Approved :: MIT License
Classifier: Operating System :: OS Independent
Requires-Python: >=3.6
Requires-Dist: requests
Requires-Dist: tqdm
Requires-Dist: Beautifulsoup4
